bitmerchantx/__init__.py
bitmerchantx/_version.py
bitmerchantx/network.py
bitmerchantx/wallet/__init__.py
bitmerchantx/wallet/bip32.py
bitmerchantx/wallet/keys.py
bitmerchantx/wallet/utils.py
bitmerchantx-0.1.9.dist-info/DESCRIPTION.rst
bitmerchantx-0.1.9.dist-info/METADATA
bitmerchantx-0.1.9.dist-info/RECORD
bitmerchantx-0.1.9.dist-info/WHEEL
bitmerchantx-0.1.9.dist-info/metadata.json
bitmerchantx-0.1.9.dist-info/top_level.txt
