Metadata-Version: 2.0
Name: bitmerchantx
Version: 0.1.9
Summary: BitCore BTX merchant tools
Home-page: https://github.com/dalijolijo/bitmerchantx
Author: David Bergen
Author-email: david.bergen@gmx.net
License: MIT License
Download-URL: https://github.com/dalijolijo/bitmerchantx/tarball/v0.1.9
Platform: UNKNOWN
Classifier: Development Status :: 3 - Alpha
Classifier: Intended Audience :: Developers
Classifier: License :: OSI Approved :: MIT License
Classifier: Operating System :: OS Independent
Classifier: Programming Language :: Python
Classifier: Programming Language :: Python :: 2.5
Classifier: Programming Language :: Python :: 2.6
Classifier: Programming Language :: Python :: 2.7
Classifier: Programming Language :: Python :: 3
Classifier: Programming Language :: Python :: 3.0
Classifier: Programming Language :: Python :: 3.1
Classifier: Programming Language :: Python :: 3.2
Classifier: Programming Language :: Python :: 3.3
Classifier: Programming Language :: Python :: 3.4
Requires-Dist: base58 (>=0.2.1)
Requires-Dist: cachetools (>=1.1.1)
Requires-Dist: ecdsa (>=0.10)
Requires-Dist: six (>=1.5.2)
